dramatic.py
dramatic-0.5.0.dist-info/METADATA
dramatic-0.5.0.dist-info/WHEEL
dramatic-0.5.0.dist-info/RECORD
