Metadata-Version: 2.1
Name: dramatic
Version: 0.5.0
Summary: Display all Python process output character-by-character
Project-URL: Documentation, https://github.com/treyhunner/dramatic#readme
Project-URL: Issues, https://github.com/treyhunner/dramatic/issues
Project-URL: Source, https://github.com/treyhunner/dramatic
Author: Trey Hunner
License: MIT
Keywords: Python Morsels,TTY,modem,teletype,terminal,typewriter
Classifier: Development Status :: 4 - Beta
Classifier: License :: OSI Approved :: MIT License
Classifier: Programming Language :: Python
Classifier: Programming Language :: Python :: 3.9
Classifier: Programming Language :: Python :: 3.10
Classifier: Programming Language :: Python :: 3.11
Classifier: Programming Language :: Python :: 3.12
Classifier: Programming Language :: Python :: 3.13
Classifier: Programming Language :: Python :: 3.14
Classifier: Programming Language :: Python :: Implementation :: CPython
Classifier: Programming Language :: Python :: Implementation :: PyPy
Requires-Python: >=3.9
